styrofoam/__init__.py
styrofoam/router.py
styrofoam/utils.py
styrofoam-1.0.0a3.dist-info/LICENSE
styrofoam-1.0.0a3.dist-info/METADATA
styrofoam-1.0.0a3.dist-info/WHEEL
styrofoam-1.0.0a3.dist-info/top_level.txt
styrofoam-1.0.0a3.dist-info/RECORD
